conversor_nominas_bancos_chile/__init__.py
conversor_nominas_bancos_chile/bancos_codigos.json
conversor_nominas_bancos_chile/bancos_headers_nomina.json
conversor_nominas_bancos_chile/bank_functions.py
conversor_nominas_bancos_chile/bank_tkinter.py
conversor_nominas_bancos_chile/bank_tkinter_menu.py
conversor_nominas_bancos_chile/planillas_test/datos_empresas.xlsx
conversor_nominas_bancos_chile/planillas_test/input_nomina_bci_ejemplo.xls
conversor_nominas_bancos_chile-1.8.5.dist-info/entry_points.txt
conversor_nominas_bancos_chile-1.8.5.dist-info/LICENSE
conversor_nominas_bancos_chile-1.8.5.dist-info/WHEEL
conversor_nominas_bancos_chile-1.8.5.dist-info/METADATA
conversor_nominas_bancos_chile-1.8.5.dist-info/RECORD
