Metadata-Version: 2.1
Name: conversor-nominas-bancos-chile
Version: 1.8.5
Summary: Librería que convierte el formato de nóminas del BCI al formato del resto de bancos.
Home-page: https://github.com/tonicanada/conversor_nominas_bancos_chile
License: MIT
Author: Antonio Canada Momblant
Author-email: toni.cm@gmail.com
Requires-Python: >=3.10,<4.0
Classifier: License :: OSI Approved :: MIT License
Classifier: Programming Language :: Python :: 3
Classifier: Programming Language :: Python :: 3.10
Requires-Dist: datetime (>=5.1,<6.0)
Requires-Dist: numpy (>=1.24.2,<2.0.0)
Requires-Dist: openpyxl (>=3.1.2,<4.0.0)
Requires-Dist: pandas (>=1.5.3,<2.0.0)
Requires-Dist: pathlib (>=1.0.1,<2.0.0)
Requires-Dist: tk (>=0.1.0,<0.2.0)
Requires-Dist: xlrd (>=2.0.1,<3.0.0)
Project-URL: Repository, https://github.com/tonicanada/conversor_nominas_bancos_chile
